flask_db/__init__.py
flask_db/cli.py
flask_db/init.py
flask_db/templates/alembic.ini
flask_db/templates/db/__init__.py
flask_db/templates/db/env.py
flask_db/templates/db/script.py.mako
flask_db/templates/db/seeds.py
flask_db/templates/db/versions/.keep
Flask_DB-0.4.1.dist-info/LICENSE
Flask_DB-0.4.1.dist-info/METADATA
Flask_DB-0.4.1.dist-info/WHEEL
Flask_DB-0.4.1.dist-info/entry_points.txt
Flask_DB-0.4.1.dist-info/top_level.txt
Flask_DB-0.4.1.dist-info/RECORD
